README.txt
setup.py
docs/HISTORY.txt
docs/INSTALL.txt
docs/LICENSE.GPL
docs/LICENSE.txt
redturtle/__init__.py
redturtle.hide_subtypes.egg-info/PKG-INFO
redturtle.hide_subtypes.egg-info/SOURCES.txt
redturtle.hide_subtypes.egg-info/dependency_links.txt
redturtle.hide_subtypes.egg-info/entry_points.txt
redturtle.hide_subtypes.egg-info/namespace_packages.txt
redturtle.hide_subtypes.egg-info/not-zip-safe
redturtle.hide_subtypes.egg-info/paster_plugins.txt
redturtle.hide_subtypes.egg-info/requires.txt
redturtle.hide_subtypes.egg-info/top_level.txt
redturtle/hide_subtypes/__init__.py
redturtle/hide_subtypes/configure.zcml
redturtle/hide_subtypes/browser/__init__.py
redturtle/hide_subtypes/browser/configure.zcml
redturtle/hide_subtypes/browser/hide_subtypes.css
redturtle/hide_subtypes/browser/please_hide_subtyper.js
redturtle/hide_subtypes/profiles/default/cssregistry.xml
redturtle/hide_subtypes/profiles/default/jsregistry.xml
redturtle/hide_subtypes/profiles/default/metadata.xml