Metadata-Version: 1.0
Name: redturtle.hide-subtypes
Version: 0.1.0
Summary: A jQuery snippet that hide the "Sub-types" menu of p4a.subtyper when empty
Home-page: http://svn.plone.org/svn/collective/redturtle.hide_subtypes
Author: RedTurtle Technology
Author-email: sviluppoplone@redturtle.net
License: GPL
Keywords: subtyper p4a plone javascript jquery menu
Platform: UNKNOWN
Classifier: Framework :: Plone
Classifier: Programming Language :: Python
Classifier: Topic :: Software Development :: Libraries :: Python Modules
